MANIFEST.in
README.md
setup.py
hgflow_official.egg-info/PKG-INFO
hgflow_official.egg-info/SOURCES.txt
hgflow_official.egg-info/dependency_links.txt
hgflow_official.egg-info/top_level.txt
src/hgflow.py