Metadata-Version: 1.1
Name: hgflow-official
Version: 0.9.8.5
Summary: Mercurial plugin to support the generalized Driessen branching model
Home-page: https://hg.sr.ht/~wu/hgflow
Author: Yujie Wu
Author-email: yujie.wu2@gmail.com
License: GPLv2
Platform: UNKNOWN
Classifier: Environment :: Plugins
Classifier: Intended Audience :: Developers
Classifier: Operating System :: OS Independent
Classifier: Programming Language :: Python
Classifier: License :: OSI Approved :: GNU General Public License v2 (GPLv2)
Classifier: Topic :: Software Development :: Version Control
